Workbook

Sheet Configuration
A1: TREASURY MANAGEMENT SYSTEM - CONFIGURATION
A3: Parameter | B3: Value | C3: Description
A4: Base_Currency | B4: SAR | C4: All final amounts convert to SAR
A5: Payment_Day | B5: 4 | C5: Wednesday (1=Sunday in Saudi week)
A6: Weekend_Days | B6: 6,7 | C6: Friday, Saturday (Saudi weekend)
A7: Week_Start | B7: Sunday | C7: Saudi calendar standard
A8: Auto_Postpone_Enabled | B8: TRUE | C8: System auto-escalates overdue items
A9: Volatile_Buffer_Near | B9: 0.02 | C9: Buffer for Week 1-2 projections (2%)
A10: Volatile_Buffer_Far | B10: 0.1 | C10: Buffer for Week 4+ projections (10%)
A11: Reference_Wednesday | B11: 2025-12-10 | C11: Base date for Wednesday calculations
A12: Surplus_Threshold | B12: 1000000 | C12: SAR threshold for surplus alert
A13: Gap_Threshold | B13: -500000 | C13: SAR threshold for critical gap alert
A14: TD_Default_Rate | B14: 0.05 | C14: Default Time Deposit rate (5%)
A15: Fiscal_Year_Start | B15: 01-01 | C15: Fiscal year start (MM-DD)
A18: VENDOR TIER CLASSIFICATION
A19: Tier | B19: Classification | C19: Payment Policy
A20: 1 | B20: Critical | C20: Government, utilities, payroll, strategic partners - Zero tolerance for delay, Pay BEFORE due date
A21: 2 | B21: Standard | C21: Regular operational vendors - Standard Wednesday payment terms
A22: 3 | B22: Flexible | C22: Vendors with negotiable terms - Maximum float optimization, Pay AFTER due date
A25: PAYMENT STATUS CODES
A26: Status | B26: Code | C26: Color | D26: Description
A27: Pending | B27: PND | C27: Amber | D27: Awaiting payment execution
A28: Paid | B28: PAID | C28: Green | D28: Successfully executed
A29: Postponed-1 | B29: PST1 | C29: Orange | D29: First automatic postponement
A30: Postponed-2+ | B30: PST2 | C30: Red | D30: Multiple postponements - requires management attention
A31: Urgent | B31: URG | C31: Purple | D31: Bypasses Wednesday rule
A32: Cancelled | B32: CAN | C32: Grey | D32: Voided payment

Sheet Exchange_Rates
A1: EXCHANGE RATE TABLE
A3: Currency | B3: Rate_to_SAR | C3: Effective_Date | D3: Last_Updated_By
A4: SAR | B4: 1 | C4: 46001.873 | D4: System
A5: USD | B5: 3.75 | C5: 46001.873 | D5: System
A6: AED | B6: 1.02 | C6: 46001.873 | D6: System
A7: EUR | B7: 4.05 | C7: 46001.873 | D7: System
A8: GBP | B8: 4.72 | C8: 46001.873 | D8: System
A9: SGD | B9: 2.81 | C9: 46001.873 | D9: System
A10: JPY | B10: 0.025 | C10: 46001.873 | D10: System
A11: CHF | B11: 4.2 | C11: 46001.873 | D11: System
A13: CONVERSION FORMULA:
A14: =Amount_Original * VLOOKUP(Currency_Code, Exchange_Rates!A4:B11, 2, FALSE)

Sheet Data_Hub
A1: MASTER DATA HUB - SINGLE SOURCE OF TRUTH
A2: IDENTITY | D2: COUNTERPARTY | G2: DATES | J2: AMOUNTS | N2: STATUS ENGINE | R2: AUDIT
A3: Payment_ID | B3: Type_Code | C3: Category | D3: Vendor_Name | E3: Vendor_Tier | F3: Contact | G3: Raw_Due_Date | H3: Target_Wednesday | I3: Value_Date | J3: Amount_Original | K3: Currency_Code | L3: FX_Rate | M3: Amount_SAR | N3: Payment_Status | O3: Postpone_Count | P3: Last_Action_Date | Q3: Priority_Flag | R3: Created_Date | S3: Created_By | T3: Modified_Date | U3: Modified_By | V3: Notes
A4: PAY-2024-001 | B4: AP | C4: OPEX | D4: Vendor Alpha Co. | E4: 1 | F4: contact@alpha.com | G4: 45641 | H4: =IF(OR($Q4="URGENT",$Q4="PAYROLL"),$G4,IF($E4=1,$G4-MOD($G4-DATE(2024,12,11),7),$G4+MOD(DATE(2024,12,11)-$G4+7,7))) | J4: 50000 | K4: USD | L4: 3.75 | M4: =$J4*$L4 | N4: PND | O4: 0 | Q4: NORMAL | R4: 46001.873 | S4: Admin | V4: Regular vendor payment
A5: PAY-2024-002 | B5: AP | C5: GOV | D5: GOSI Payment | E5: 1 | F5: gov@gosi.sa | G5: 45636 | H5: =IF(OR($Q5="URGENT",$Q5="PAYROLL"),$G5,IF($E5=1,$G5-MOD($G5-DATE(2024,12,11),7),$G5+MOD(DATE(2024,12,11)-$G5+7,7))) | J5: 125000 | K5: SAR | L5: 1 | M5: =$J5*$L5 | N5: PND | O5: 0 | Q5: URGENT | R5: 46001.873 | S5: Admin | V5: Government obligation
A6: PAY-2024-003 | B6: AP | C6: HR | D6: Monthly Payroll | E6: 1 | F6: hr@company.com | G6: 45651 | H6: =IF(OR($Q6="URGENT",$Q6="PAYROLL"),$G6,IF($E6=1,$G6-MOD($G6-DATE(2024,12,11),7),$G6+MOD(DATE(2024,12,11)-$G6+7,7))) | J6: 2500000 | K6: SAR | L6: 1 | M6: =$J6*$L6 | N6: PND | O6: 0 | Q6: PAYROLL | R6: 46001.873 | S6: Admin | V6: December payroll
A7: PAY-2024-004 | B7: AP | C7: OPEX | D7: Supplier Beta Ltd | E7: 2 | F7: pay@beta.com | G7: 45644 | H7: =IF(OR($Q7="URGENT",$Q7="PAYROLL"),$G7,IF($E7=1,$G7-MOD($G7-DATE(2024,12,11),7),$G7+MOD(DATE(2024,12,11)-$G7+7,7))) | J7: 75000 | K7: EUR | L7: 4.05 | M7: =$J7*$L7 | N7: PND | O7: 0 | Q7: NORMAL | R7: 46001.873 | S7: Admin | V7: Quarterly supplies
A8: PAY-2024-005 | B8: AP | C8: LOAN | D8: Bank Loan Principal | E8: 1 | F8: loans@bank.com | G8: 45657 | H8: =IF(OR($Q8="URGENT",$Q8="PAYROLL"),$G8,IF($E8=1,$G8-MOD($G8-DATE(2024,12,11),7),$G8+MOD(DATE(2024,12,11)-$G8+7,7))) | J8: 500000 | K8: SAR | L8: 1 | M8: =$J8*$L8 | N8: PND | O8: 0 | Q8: NORMAL | R8: 46001.873 | S8: Admin | V8: Loan installment
A9: PAY-2024-006 | B9: AP | C9: OPEX | D9: Flexible Supplier X | E9: 3 | F9: accounts@supplierx.com | G9: 45646 | H9: =IF(OR($Q9="URGENT",$Q9="PAYROLL"),$G9,IF($E9=1,$G9-MOD($G9-DATE(2024,12,11),7),$G9+MOD(DATE(2024,12,11)-$G9+7,7))) | J9: 30000 | K9: AED | L9: 1.02 | M9: =$J9*$L9 | N9: PND | O9: 0 | Q9: NORMAL | R9: 46001.873 | S9: Admin | V9: Negotiable terms

Sheet Time_Deposits
A1: TIME DEPOSIT TRACKING MODULE
A3: TD_ID | B3: Bank | C3: Account_No | D3: Currency | E3: Start_Date | F3: Maturity_Date | G3: Principal_Original | H3: Rate_Percent | I3: Days | J3: Profit_Original | K3: Maturity_Amount | L3: Status | M3: Week_ID | N3: Principal_SAR | O3: Profit_SAR
A4: TD-2024-001 | B4: Al Rajhi Bank | C4: SA1234567890 | D4: SAR | E4: 45597 | F4: 45641 | G4: 5000000 | H4: 0.055 | I4: =$F4-$E4 | J4: =$G4*$H4*$I4/365 | K4: =$G4+$J4 | L4: =IF($F4<TODAY(),"CLOSED",IF($F4=TODAY(),"ACTION REQUIRED","ACTIVE")) | M4: =WEEKNUM($F4,2) | N4: =IF($D4="SAR",$G4,$G4*VLOOKUP($D4,Exchange_Rates!$A$4:$B$11,2,FALSE)) | O4: =IF($D4="SAR",$J4,$J4*VLOOKUP($D4,Exchange_Rates!$A$4:$B$11,2,FALSE))
A5: TD-2024-002 | B5: Saudi National Bank | C5: SA0987654321 | D5: SAR | E5: 45611 | F5: 45646 | G5: 3000000 | H5: 0.052 | I5: =$F5-$E5 | J5: =$G5*$H5*$I5/365 | K5: =$G5+$J5 | L5: =IF($F5<TODAY(),"CLOSED",IF($F5=TODAY(),"ACTION REQUIRED","ACTIVE")) | M5: =WEEKNUM($F5,2) | N5: =IF($D5="SAR",$G5,$G5*VLOOKUP($D5,Exchange_Rates!$A$4:$B$11,2,FALSE)) | O5: =IF($D5="SAR",$J5,$J5*VLOOKUP($D5,Exchange_Rates!$A$4:$B$11,2,FALSE))
A6: TD-2024-003 | B6: SABB | C6: SA1122334455 | D6: USD | E6: 45566 | F6: 45657 | G6: 1000000 | H6: 0.048 | I6: =$F6-$E6 | J6: =$G6*$H6*$I6/365 | K6: =$G6+$J6 | L6: =IF($F6<TODAY(),"CLOSED",IF($F6=TODAY(),"ACTION REQUIRED","ACTIVE")) | M6: =WEEKNUM($F6,2) | N6: =IF($D6="SAR",$G6,$G6*VLOOKUP($D6,Exchange_Rates!$A$4:$B$11,2,FALSE)) | O6: =IF($D6="SAR",$J6,$J6*VLOOKUP($D6,Exchange_Rates!$A$4:$B$11,2,FALSE))
A7: TD-2024-004 | B7: Riyad Bank | C7: SA5544332211 | D7: SAR | E7: 45627 | F7: 45672 | G7: 2000000 | H7: 0.05 | I7: =$F7-$E7 | J7: =$G7*$H7*$I7/365 | K7: =$G7+$J7 | L7: =IF($F7<TODAY(),"CLOSED",IF($F7=TODAY(),"ACTION REQUIRED","ACTIVE")) | M7: =WEEKNUM($F7,2) | N7: =IF($D7="SAR",$G7,$G7*VLOOKUP($D7,Exchange_Rates!$A$4:$B$11,2,FALSE)) | O7: =IF($D7="SAR",$J7,$J7*VLOOKUP($D7,Exchange_Rates!$A$4:$B$11,2,FALSE))
A8: TD-2024-005 | B8: Al Rajhi Bank | C8: SA9988776655 | D8: SAR | E8: 45631 | F8: 45693 | G8: 4000000 | H8: 0.053 | I8: =$F8-$E8 | J8: =$G8*$H8*$I8/365 | K8: =$G8+$J8 | L8: =IF($F8<TODAY(),"CLOSED",IF($F8=TODAY(),"ACTION REQUIRED","ACTIVE")) | M8: =WEEKNUM($F8,2) | N8: =IF($D8="SAR",$G8,$G8*VLOOKUP($D8,Exchange_Rates!$A$4:$B$11,2,FALSE)) | O8: =IF($D8="SAR",$J8,$J8*VLOOKUP($D8,Exchange_Rates!$A$4:$B$11,2,FALSE))
A12: MATURITY LADDER (LIQUIDITY PLANNING)
A13: Period | B13: Principal Maturing (SAR) | C13: Interest Earned (SAR) | D13: Total Available | E13: Count | F13: Cumulative
A14: This Week | B14: =SUMIFS($N$4:$N$100,$M$4:$M$100,WEEKNUM(TODAY(),2)) | C14: =SUMIFS($O$4:$O$100,$M$4:$M$100,WEEKNUM(TODAY(),2)) | D14: =$B14+$C14
A15: Week +1 | B15: =SUMIFS($N$4:$N$100,$M$4:$M$100,WEEKNUM(TODAY(),2)+1) | C15: =SUMIFS($O$4:$O$100,$M$4:$M$100,WEEKNUM(TODAY(),2)+1) | D15: =$B15+$C15
A16: Week +2 | B16: =SUMIFS($N$4:$N$100,$M$4:$M$100,WEEKNUM(TODAY(),2)+2) | C16: =SUMIFS($O$4:$O$100,$M$4:$M$100,WEEKNUM(TODAY(),2)+2) | D16: =$B16+$C16
A17: Week +3 | B17: =SUMIFS($N$4:$N$100,$M$4:$M$100,WEEKNUM(TODAY(),2)+3) | C17: =SUMIFS($O$4:$O$100,$M$4:$M$100,WEEKNUM(TODAY(),2)+3) | D17: =$B17+$C17
A18: Month +1 | B18: =SUMIFS($N$4:$N$100,$F$4:$F$100,">="&DATE(YEAR(TODAY()),MONTH(TODAY())+1,1),$F$4:$F$100,"<"&DATE(YEAR(TODAY()),MONTH(TODAY())+2,1)) | C18: =SUMIFS($O$4:$O$100,$F$4:$F$100,">="&DATE(YEAR(TODAY()),MONTH(TODAY())+1,1),$F$4:$F$100,"<"&DATE(YEAR(TODAY()),MONTH(TODAY())+2,1)) | D18: =$B18+$C18
A21: BANK CONCENTRATION ANALYSIS | G21: CURRENCY BREAKDOWN
A22: Bank | B22: Active TDs | C22: Total Principal (SAR) | D22: % of Portfolio | E22: Avg Rate | G22: Currency | H22: Principal (Original) | I22: Principal (SAR) | J22: Count | K22: % of Total
A23: Al Rajhi Bank | B23: =COUNTIFS($B$4:$B$100,"Al Rajhi Bank",$L$4:$L$100,"ACTIVE") | C23: =SUMIFS($N$4:$N$100,$B$4:$B$100,"Al Rajhi Bank",$L$4:$L$100,"ACTIVE") | D23: =IFERROR($C23/SUM($C$23:$C$26),0) | E23: =IFERROR(AVERAGEIFS($H$4:$H$100,$B$4:$B$100,"Al Rajhi Bank",$L$4:$L$100,"ACTIVE"),0) | G23: SAR | H23: =SUMIFS($G$4:$G$100,$D$4:$D$100,"SAR",$L$4:$L$100,"ACTIVE") | I23: =SUMIFS($N$4:$N$100,$D$4:$D$100,"SAR",$L$4:$L$100,"ACTIVE") | J23: =COUNTIFS($D$4:$D$100,"SAR",$L$4:$L$100,"ACTIVE") | K23: =IFERROR($I23/SUM($I$23:$I$26),0)
A24: Saudi National Bank | B24: =COUNTIFS($B$4:$B$100,"Saudi National Bank",$L$4:$L$100,"ACTIVE") | C24: =SUMIFS($N$4:$N$100,$B$4:$B$100,"Saudi National Bank",$L$4:$L$100,"ACTIVE") | D24: =IFERROR($C24/SUM($C$23:$C$26),0) | E24: =IFERROR(AVERAGEIFS($H$4:$H$100,$B$4:$B$100,"Saudi National Bank",$L$4:$L$100,"ACTIVE"),0) | G24: USD | H24: =SUMIFS($G$4:$G$100,$D$4:$D$100,"USD",$L$4:$L$100,"ACTIVE") | I24: =SUMIFS($N$4:$N$100,$D$4:$D$100,"USD",$L$4:$L$100,"ACTIVE") | J24: =COUNTIFS($D$4:$D$100,"USD",$L$4:$L$100,"ACTIVE") | K24: =IFERROR($I24/SUM($I$23:$I$26),0)
A25: SABB | B25: =COUNTIFS($B$4:$B$100,"SABB",$L$4:$L$100,"ACTIVE") | C25: =SUMIFS($N$4:$N$100,$B$4:$B$100,"SABB",$L$4:$L$100,"ACTIVE") | D25: =IFERROR($C25/SUM($C$23:$C$26),0) | E25: =IFERROR(AVERAGEIFS($H$4:$H$100,$B$4:$B$100,"SABB",$L$4:$L$100,"ACTIVE"),0) | G25: EUR | H25: =SUMIFS($G$4:$G$100,$D$4:$D$100,"EUR",$L$4:$L$100,"ACTIVE") | I25: =SUMIFS($N$4:$N$100,$D$4:$D$100,"EUR",$L$4:$L$100,"ACTIVE") | J25: =COUNTIFS($D$4:$D$100,"EUR",$L$4:$L$100,"ACTIVE") | K25: =IFERROR($I25/SUM($I$23:$I$26),0)
A26: Riyad Bank | B26: =COUNTIFS($B$4:$B$100,"Riyad Bank",$L$4:$L$100,"ACTIVE") | C26: =SUMIFS($N$4:$N$100,$B$4:$B$100,"Riyad Bank",$L$4:$L$100,"ACTIVE") | D26: =IFERROR($C26/SUM($C$23:$C$26),0) | E26: =IFERROR(AVERAGEIFS($H$4:$H$100,$B$4:$B$100,"Riyad Bank",$L$4:$L$100,"ACTIVE"),0) | G26: GBP | H26: =SUMIFS($G$4:$G$100,$D$4:$D$100,"GBP",$L$4:$L$100,"ACTIVE") | I26: =SUMIFS($N$4:$N$100,$D$4:$D$100,"GBP",$L$4:$L$100,"ACTIVE") | J26: =COUNTIFS($D$4:$D$100,"GBP",$L$4:$L$100,"ACTIVE") | K26: =IFERROR($I26/SUM($I$23:$I$26),0)

Sheet Payment_Calendar
A1: PAYMENT CALENDAR - WEDNESDAY PAYMENT SCHEDULE
A3: Category | B3: Vendor | C3: Status | D3: Amount_SAR | E3: 45998.873 | F3: 45999.873 | G3: 46000.873 | H3: 46001.873 | I3: 46002.873 | J3: 46003.873 | K3: 46004.873 | L3: 46005.873 | M3: 46006.873 | N3: 46007.873 | O3: 46008.873 | P3: 46009.873 | Q3: 46010.873 | R3: 46011.873 | S3: 46012.873 | T3: 46013.873 | U3: 46014.873 | V3: 46015.873 | W3: 46016.873 | X3: 46017.873 | Y3: 46018.873 | Z3: 46019.873 | AA3: 46020.873 | AB3: 46021.873 | AC3: 46022.873 | AD3: 46023.873 | AE3: 46024.873 | AF3: 46025.873 | AG3: 46026.873 | AH3: 46027.873
A4: OPERATING EXPENSES (OPEX)
B5: Vendor Alpha Co. | C5: PND | D5: 187500
B6: Supplier Beta Ltd | C6: PND | D6: 303750
B7: Flexible Supplier X | C7: PND | D7: 30600
A8: HUMAN RESOURCES
B9: Monthly Payroll | C9: PND | D9: 2500000
B10: End of Service | C10: PND | D10: 0
B11: Benefits & Allowances | C11: PND | D11: 0
A12: GOVERNMENT OBLIGATIONS
B13: VAT Payment | C13: PND | D13: 0
B14: GOSI Payment | C14: URG | D14: 125000
B15: Zakat | C15: PND | D15: 0
A16: STRATEGIC PAYMENTS
B17: Partner X | C17: PND | D17: 0
B18: Partner Y | C18: PND | D18: 0
A19: LOAN SERVICING
B20: Bank Loan Principal | C20: PND | D20: 500000
B21: Bank Loan Interest | C21: PND | D21: 0
A23: TOTAL PAYMENTS | D23: =SUM(D5:D22) | E23: =SUM(E5:E22) | F23: =SUM(F5:F22) | G23: =SUM(G5:G22) | H23: =SUM(H5:H22) | I23: =SUM(I5:I22) | J23: =SUM(J5:J22) | K23: =SUM(K5:K22) | ... AH23: =SUM(AH5:AH22)

Sheet Treasury_Calendar
A1: TREASURY CALENDAR - CASH POSITION VIEW
A3: Metric | B3: 10-Dec | C3: 17-Dec | D3: 24-Dec | E3: 31-Dec | F3: 07-Jan | G3: 14-Jan | H3: 21-Jan | I3: 28-Jan
A4: DEMAND STREAM (OUTFLOWS)
A5: Confirmed AP (Tier 1-2) | B5: 875000 | C5: 650000 | D5: 420000 | E5: 380000 | F5: 290000 | G5: 350000 | H5: 400000 | I5: 320000
A6: Estimated AP (Recurring) | B6: 150000 | C6: 150000 | D6: 150000 | E6: 150000 | F6: 150000 | G6: 150000 | H6: 150000 | I6: 150000
A7: Payroll | B7: 0 | C7: 0 | D7: 0 | E7: 2500000 | F7: 0 | G7: 0 | H7: 0 | I7: 0
A8: Government Obligations | B8: 125000 | C8: 0 | D8: 0 | E8: 0 | F8: 0 | G8: 0 | H8: 0 | I8: 0
A9: Loan Servicing | B9: 0 | C9: 0 | D9: 0 | E9: 500000 | F9: 0 | G9: 0 | H9: 0 | I9: 0
A10: Volatile Buffer | B10: =SUM(B5:B9)*0.02 | C10: =SUM(C5:C9)*0.02 | D10: =SUM(D5:D9)*0.1 | E10: =SUM(E5:E9)*0.1 | F10: =SUM(F5:F9)*0.1 | G10: =SUM(G5:G9)*0.1 | H10: =SUM(H5:H9)*0.1 | I10: =SUM(I5:I9)*0.1
A11: TOTAL CASH REQUIRED | B11: =SUM(B5:B10) | C11: =SUM(C5:C10) | D11: =SUM(D5:D10) | E11: =SUM(E5:E10) | F11: =SUM(F5:F10) | G11: =SUM(G5:G10) | H11: =SUM(H5:H10) | I11: =SUM(I5:I10)
A13: SUPPLY STREAM (INFLOWS)
A14: Maturing TD Principal | B14: 5000000 | C14: 3000000 | D14: 0 | E14: 0 | F14: 2000000 | G14: 4000000 | H14: 0 | I14: 0
A15: Maturing TD Interest | B15: 45000 | C15: 27000 | D15: 0 | E15: 0 | F15: 15000 | G15: 35000 | H15: 0 | I15: 0
A16: Operating Cash | B16: 500000 | C16: 500000 | D16: 500000 | E16: 500000 | F16: 500000 | G16: 500000 | H16: 500000 | I16: 500000
A17: AR Collections | B17: 350000 | C17: 400000 | D17: 380000 | E17: 420000 | F17: 390000 | G17: 410000 | H17: 400000 | I17: 380000
A18: TOTAL CASH AVAILABLE | B18: =SUM(B14:B17) | C18: =SUM(C14:C17) | D18: =SUM(D14:D17) | E18: =SUM(E14:E17) | F18: =SUM(F14:F17) | G18: =SUM(G14:G17) | H18: =SUM(H14:H17) | I18: =SUM(I14:I17)
A20: DELTA ENGINE
A21: NET POSITION (Delta) | B21: =B18-B11 | C21: =C18-C11 | D21: =D18-D11 | E21: =E18-E11 | F21: =F18-F11 | G21: =G18-G11 | H21: =H18-H11 | I21: =I18-I11
A22: ACTION FLAG | B22: =IF(B21>1000000,"SURPLUS - Roll to TD",IF(B21<-500000,"GAP - Book TD or Draw OD","BALANCED")) | C22: =IF(C21>1000000,"SURPLUS - Roll to TD",IF(C21<-500000,"GAP - Book TD or Draw OD","BALANCED")) | D22: =IF(D21>1000000,"SURPLUS - Roll to TD",IF(D21<-500000,"GAP - Book TD or Draw OD","BALANCED")) | E22: =IF(E21>1000000,"SURPLUS - Roll to TD",IF(E21<-500000,"GAP - Book TD or Draw OD","BALANCED")) | F22: =IF(F21>1000000,"SURPLUS - Roll to TD",IF(F21<-500000,"GAP - Book TD or Draw OD","BALANCED")) | G22: =IF(G21>1000000,"SURPLUS - Roll to TD",IF(G21<-500000,"GAP - Book TD or Draw OD","BALANCED")) | H22: =IF(H21>1000000,"SURPLUS - Roll to TD",IF(H21<-500000,"GAP - Book TD or Draw OD","BALANCED")) | I22: =IF(I21>1000000,"SURPLUS - Roll to TD",IF(I21<-500000,"GAP - Book TD or Draw OD","BALANCED"))

Sheet Dashboard
A1: EXECUTIVE TREASURY DASHBOARD
A2: As of: 2025-12-10 20:57
A4: KEY METRICS | F4: TODAY'S ACTION LIST
A5: Total Payments Due This Week | B5: =SUMIFS(Data_Hub!$M$4:$M$100,Data_Hub!$H$4:$H$100,">="&TODAY(),Data_Hub!$H$4:$H$100,"<"&TODAY()+7,Data_Hub!$N$4:$N$100,"<>"&"PAID") | C5: SAR | F5: Item | G5: Type | H5: Amount (SAR)
A6: Total TDs Maturing Today | B6: =SUMIFS(Time_Deposits!$N$4:$N$100,Time_Deposits!$F$4:$F$100,TODAY()) | C6: SAR | F6: Payments due today | G6: AP | H6: =SUMIFS(Data_Hub!$M$4:$M$100,Data_Hub!$H$4:$H$100,TODAY())
A7: Net Cash Position (This Week) | B7: =Treasury_Calendar!B18-Treasury_Calendar!B11 | C7: SAR | F7: TDs maturing today | G7: TD | H7: =SUMIFS(Time_Deposits!$K$4:$K$100,Time_Deposits!$F$4:$F$100,TODAY())
A8: Overdue Payments Count | B8: =COUNTIFS(Data_Hub!$N$4:$N$100,"PST*") | C8: Count | F8: Escalated items (PST2) | G8: Escalation | H8: =SUMIFS(Data_Hub!$M$4:$M$100,Data_Hub!$N$4:$N$100,"PST2")
A9: Urgent Items | B9: =COUNTIFS(Data_Hub!$N$4:$N$100,"URG") | C9: Count
A10: Active Time Deposits | B10: =COUNTIFS(Time_Deposits!$L$4:$L$100,"ACTIVE") | C10: Count
A11: Total TD Principal (Active) | B11: =SUMIFS(Time_Deposits!$N$4:$N$100,Time_Deposits!$L$4:$L$100,"ACTIVE") | C11: SAR
A14: ALERT FLAGS | F14: WEEKLY CASH FLOW SUMMARY
A15: Alert Type | B15: Status | C15: Count/Value | D15: Action Required | F15: Week | G15: Outflows | H15: Inflows
A16: Critical Gap | B16: =IF(Treasury_Calendar!B18<-500000,"YES","NO") | C16: =IF(Treasury_Calendar!B18<-500000,Treasury_Calendar!B18,"-") | D16: Review cash position immediately | F16: This Week | G16: =Treasury_Calendar!B11 | H16: =Treasury_Calendar!B18
A17: Escalated Payment (PST2) | B17: =IF(COUNTIFS(Data_Hub!$N$4:$N$100,"PST2")>0,"YES","NO") | C17: =COUNTIFS(Data_Hub!$N$4:$N$100,"PST2") | D17: Management approval required | F17: Week +1 | G17: =Treasury_Calendar!C11 | H17: =Treasury_Calendar!C18
A18: TD Action Required | B18: =IF(COUNTIFS(Time_Deposits!$L$4:$L$100,"ACTION REQUIRED")>0,"YES","NO") | C18: =COUNTIFS(Time_Deposits!$L$4:$L$100,"ACTION REQUIRED") | D18: Decide on matured TD | F18: Week +2 | G18: =Treasury_Calendar!D11 | H18: =Treasury_Calendar!D18
A19: Surplus Available | B19: =IF(Treasury_Calendar!B18>1000000,"YES","NO") | C19: =IF(Treasury_Calendar!B18>1000000,Treasury_Calendar!B18,"-") | D19: Consider rolling to TD | F19: Week +3 | G19: =Treasury_Calendar!E11 | H19: =Treasury_Calendar!E18

Sheet Validation
A1: VALIDATION & AUDIT FRAMEWORK
A3: DATA INTEGRITY CHECKS
A4: Validation Check | B4: Formula | C4: Result | D4: Status
A5: Payment Total Reconciliation | B5: =SUM(Data_Hub!$M$4:$M$100)=SUM(Payment_Calendar!$D$5:$D$25) | C5: =IF(SUM(Data_Hub!$M$4:$M$100)=SUM(Payment_Calendar!$D$5:$D$25),"PASS","FAIL") | D5: Verify payment calendar matches data hub
A6: TD Principal Balance | B6: =SUM(Time_Deposits!$N$4:$N$100) | C6: =SUM(Time_Deposits!$N$4:$N$100) | D6: Total TD principal
A7: Missing Required Fields | B7: =COUNTBLANK(Data_Hub!$A$4:$A$100)+COUNTBLANK(Data_Hub!$G$4:$G$100) | C7: =IF(COUNTBLANK(Data_Hub!$A$4:$A$100)+COUNTBLANK(Data_Hub!$G$4:$G$100)=0,"COMPLETE","INCOMPLETE") | D7: Check for missing payment IDs or dates
A8: Invalid Status Codes | B8: =COUNTIF(Data_Hub!$N$4:$N$100,"<>PND")-COUNTIF(Data_Hub!$N$4:$N$100,"PAID")-COUNTIF(Data_Hub!$N$4:$N$100,"PST*")-COUNTIF(Data_Hub!$N$4:$N$100,"URG")-COUNTIF(Data_Hub!$N$4:$N$100,"CAN") | C8: =IF(COUNTIF(Data_Hub!$N$4:$N$100,"<>PND")-COUNTIF(Data_Hub!$N$4:$N$100,"PAID")-SUMPRODUCT((LEFT(Data_Hub!$N$4:$N$100,3)="PST")*1)-COUNTIF(Data_Hub!$N$4:$N$100,"URG")-COUNTIF(Data_Hub!$N$4:$N$100,"CAN")<=0,"VALID","INVALID") | D8: Verify all status codes are valid
A9: Currency Code Validation | B9: =SUMPRODUCT((ISERROR(MATCH(Data_Hub!$K$4:$K$100,Exchange_Rates!$A$4:$A$11,0)))*1) | C9: =IF(SUMPRODUCT((ISERROR(MATCH(Data_Hub!$K$4:$K$100,Exchange_Rates!$A$4:$A$11,0)))*1)=0,"VALID","INVALID") | D9: All currency codes must exist in exchange rates
A13: PERIOD SELECTOR CONFIGURATION
A14: Selector | B14: Options | C14: Current Value | D14: Description
A15: Period Type | B15: Weekly / Monthly / Quarterly / Yearly | C15: Weekly | D15: Changes filter scope
A16: Week ID | B16: 01-52 | C16: 50 | D16: Filters to specific Saudi week (Sunday start)
A17: Month | B17: Jan-Dec | C17: Dec | D17: Filters to calendar month
A18: Quarter | B18: Q1-Q4 | C18: Q4 | D18: Filters to quarter
A19: Year | B19: 2024, 2025, ... | C19: 2024 | D19: Filters to full year
A22: SYSTEM INFORMATION
A23: Workbook Version | B23: 1.0.0
A24: Created Date | B24: 2025-12-10
A25: Last Modified | B25: 2025-12-10 20:57:26
A26: Base Currency | B26: SAR
A27: Week Configuration | B27: Saudi (Sunday Start)
A28: Payment Day | B28: Wednesday (Day 4)
